otel_utils/__init__.py
otel_utils/configurator.py
otel_utils/logging.py
otel_utils/metrics.py
otel_utils/tracing.py
otel_utils-1.1.1.dist-info/METADATA
otel_utils-1.1.1.dist-info/WHEEL
otel_utils-1.1.1.dist-info/RECORD
