Metadata-Version: 2.3
Name: otel-utils
Version: 1.1.1
Summary: Utilidades simplificadas para instrumentación con OpenTelemetry
License: Proprietary
Author: Harold Portocarrero
Author-email: harold@getcometa.com
Requires-Python: >=3.8
Classifier: License :: Other/Proprietary License
Classifier: Programming Language :: Python :: 3
Classifier: Programming Language :: Python :: 3.8
Classifier: Programming Language :: Python :: 3.9
Classifier: Programming Language :: Python :: 3.10
Classifier: Programming Language :: Python :: 3.11
Classifier: Programming Language :: Python :: 3.12
Classifier: Programming Language :: Python :: 3.13
Requires-Dist: opentelemetry-api (>=1.29.0)
Requires-Dist: opentelemetry-exporter-otlp (>=1.29.0)
Requires-Dist: opentelemetry-instrumentation (>=0.50b0)
Requires-Dist: opentelemetry-instrumentation-logging (>=0.50b0)
Requires-Dist: opentelemetry-sdk (>=1.29.0)
Requires-Dist: typing-extensions (>=4.12.2)
Project-URL: Repository, https://github.com/getcometa/otel-utils
